<?xml version="1.0" encoding="UTF-8"?>

<document>
  <segment instanceid="news_wsj_0158.txt_1" begin="4" end="29">
    <text>Reuters Holdings PLC said</text>
    <mainVerb begin="25" end="29">said</mainVerb>
    <mainReferent begin="21" end="24">PLC</mainReferent>
    <annotation annotator="gold" seType="REPORT" mainReferentGenericity="NON-GENERIC" habituality="EPISODIC" mainVerbAspectualClass="DYNAMIC"/>
    <annotation annotator="B" seType="REPORT:EVENT" mainReferentGenericity="NON-GENERIC" habituality="EPISODIC" mainVerbAspectualClass="DYNAMIC"/>
    <annotation annotator="D" seType="REPORT:EVENT" mainReferentGenericity="NON-GENERIC" habituality="EPISODIC" mainVerbAspectualClass="DYNAMIC"/>
    <annotation annotator="C" seType="REPORT:EVENT" mainReferentGenericity="NON-GENERIC" habituality="EPISODIC" mainVerbAspectualClass="DYNAMIC"/>
  </segment>
  <segment instanceid="news_wsj_0158.txt_2" begin="30" end="112">
    <text>Michael Reupke resigned as general manager to pursue unspecified interests, a move</text>
    <mainVerb begin="45" end="53">resigned</mainVerb>
    <mainReferent begin="38" end="44">Reupke</mainReferent>
    <annotation annotator="gold" seType="EVENT" mainReferentGenericity="NON-GENERIC" habituality="EPISODIC" mainVerbAspectualClass="DYNAMIC"/>
    <annotation annotator="B" seType="EVENT" mainReferentGenericity="NON-GENERIC" habituality="EPISODIC" mainVerbAspectualClass="DYNAMIC"/>
    <annotation annotator="D" seType="EVENT" mainReferentGenericity="NON-GENERIC" habituality="EPISODIC" mainVerbAspectualClass="DYNAMIC"/>
    <annotation annotator="C" seType="EVENT" mainReferentGenericity="NON-GENERIC" habituality="EPISODIC" mainVerbAspectualClass="DYNAMIC"/>
  </segment>
  <segment instanceid="news_wsj_0158.txt_3" begin="113" end="167">
    <text>the news organization termed an "amicable separation."</text>
    <mainVerb begin="135" end="141">termed</mainVerb>
    <mainReferent begin="122" end="134">organization</mainReferent>
    <annotation annotator="gold" seType="EVENT" mainReferentGenericity="NON-GENERIC" habituality="EPISODIC" mainVerbAspectualClass="DYNAMIC"/>
    <annotation annotator="B" seType="EVENT" mainReferentGenericity="NON-GENERIC" habituality="EPISODIC" mainVerbAspectualClass="DYNAMIC"/>
    <annotation annotator="D" seType="EVENT" mainReferentGenericity="NON-GENERIC" habituality="EPISODIC" mainVerbAspectualClass="DYNAMIC"/>
    <annotation annotator="C" seType="EVENT" mainReferentGenericity="NON-GENERIC" habituality="EPISODIC" mainVerbAspectualClass="DYNAMIC"/>
  </segment>
  <segment instanceid="news_wsj_0158.txt_4" begin="171" end="307">
    <text>Mr. Reupke, 52 years old and a 27-year Reuters veteran, had been the information-services company's general manager for only six months.</text>
    <mainVerb begin="231" end="235">been</mainVerb>
    <mainReferent begin="175" end="181">Reupke</mainReferent>
    <annotation annotator="gold" seType="STATE" mainReferentGenericity="NON-GENERIC" habituality="STATIC" mainVerbAspectualClass="STATIVE"/>
    <annotation annotator="B" seType="STATE" mainReferentGenericity="NON-GENERIC" habituality="STATIC" mainVerbAspectualClass="STATIVE"/>
    <annotation annotator="D" seType="STATE" mainReferentGenericity="NON-GENERIC" habituality="STATIC" mainVerbAspectualClass="STATIVE"/>
    <annotation annotator="C" seType="STATE" mainReferentGenericity="NON-GENERIC" habituality="STATIC" mainVerbAspectualClass="STATIVE"/>
  </segment>
  <segment instanceid="news_wsj_0158.txt_5" begin="308" end="405">
    <text>His appointment to that post, which has senior administrative, staff and policy responsibilities,</text>
    <mainVerb begin="344" end="347">has</mainVerb>
    <mainReferent begin="332" end="336">post</mainReferent>
    <annotation annotator="gold" seType="STATE" mainReferentGenericity="NON-GENERIC" habituality="STATIC" mainVerbAspectualClass="STATIVE"/>
    <annotation annotator="B" seType="STATE" mainReferentGenericity="NON-GENERIC" habituality="STATIC" mainVerbAspectualClass="STATIVE"/>
    <annotation annotator="D" seType="STATE" mainReferentGenericity="NON-GENERIC" habituality="STATIC" mainVerbAspectualClass="STATIVE"/>
    <annotation annotator="C" seType="STATE" mainReferentGenericity="NON-GENERIC" habituality="STATIC" mainVerbAspectualClass="STATIVE"/>
  </segment>
  <segment instanceid="news_wsj_0158.txt_6" begin="406" end="466">
    <text>followed a several-year tenure as Reuters's editor in chief.</text>
    <mainVerb begin="406" end="414">followed</mainVerb>
    <mainReferent begin="312" end="323">appointment</mainReferent>
    <annotation annotator="gold" seType="EVENT" mainReferentGenericity="NON-GENERIC" habituality="EPISODIC" mainVerbAspectualClass="DYNAMIC"/>
    <annotation annotator="B" seType="STATE" mainReferentGenericity="NON-GENERIC" habituality="STATIC" mainVerbAspectualClass="STATIVE"/>
    <annotation annotator="D" seType="EVENT" mainReferentGenericity="NON-GENERIC" habituality="EPISODIC" mainVerbAspectualClass="DYNAMIC"/>
    <annotation annotator="C" seType="EVENT" mainReferentGenericity="NON-GENERIC" habituality="EPISODIC" mainVerbAspectualClass="DYNAMIC"/>
  </segment>
  <segment instanceid="news_wsj_0158.txt_7" begin="467" end="490">
    <text>No successor was named,</text>
    <mainVerb begin="484" end="489">named</mainVerb>
    <mainReferent begin="470" end="479">successor</mainReferent>
    <annotation annotator="gold" seType="STATE" mainReferentGenericity="NON-GENERIC" habituality="STATIC" mainVerbAspectualClass="DYNAMIC"/>
    <annotation annotator="B" seType="STATE" mainReferentGenericity="NON-GENERIC" habituality="STATIC" mainVerbAspectualClass="DYNAMIC"/>
    <annotation annotator="D" seType="STATE" mainReferentGenericity="NON-GENERIC" habituality="STATIC" mainVerbAspectualClass="DYNAMIC"/>
    <annotation annotator="C" seType="STATE" mainReferentGenericity="NON-GENERIC" habituality="STATIC" mainVerbAspectualClass="DYNAMIC"/>
  </segment>
  <segment instanceid="news_wsj_0158.txt_8" begin="491" end="573">
    <text>and Mr. Reupke's duties will be split among three other senior Reuters executives,</text>
    <mainVerb begin="523" end="528">split</mainVerb>
    <mainReferent begin="470" end="479">successor</mainReferent>
    <annotation annotator="gold" seType="STATE" mainReferentGenericity="NON-GENERIC" habituality="STATIC" mainVerbAspectualClass="DYNAMIC"/>
    <annotation annotator="B" seType="STATE" mainReferentGenericity="NON-GENERIC" habituality="STATIC" mainVerbAspectualClass="DYNAMIC"/>
    <annotation annotator="D" seType="STATE" mainReferentGenericity="NON-GENERIC" habituality="STATIC" mainVerbAspectualClass="DYNAMIC"/>
    <annotation annotator="C" seType="STATE" mainReferentGenericity="NON-GENERIC" habituality="STATIC" mainVerbAspectualClass="DYNAMIC"/>
  </segment>
  <segment instanceid="news_wsj_0158.txt_9" begin="574" end="591">
    <text>the company said.</text>
    <mainVerb begin="586" end="590">said</mainVerb>
    <mainReferent begin="578" end="585">company</mainReferent>
    <annotation annotator="gold" seType="REPORT" mainReferentGenericity="NON-GENERIC" habituality="EPISODIC" mainVerbAspectualClass="DYNAMIC"/>
    <annotation annotator="B" seType="REPORT:EVENT" mainReferentGenericity="NON-GENERIC" habituality="EPISODIC" mainVerbAspectualClass="DYNAMIC"/>
    <annotation annotator="D" seType="REPORT:EVENT" mainReferentGenericity="NON-GENERIC" habituality="EPISODIC" mainVerbAspectualClass="DYNAMIC"/>
    <annotation annotator="C" seType="REPORT:EVENT" mainReferentGenericity="NON-GENERIC" habituality="EPISODIC" mainVerbAspectualClass="DYNAMIC"/>
  </segment>
  <segment instanceid="news_wsj_0158.txt_10" begin="595" end="636">
    <text>In a telephone interview, Mr. Reupke said</text>
    <mainVerb begin="632" end="636">said</mainVerb>
    <mainReferent begin="625" end="631">Reupke</mainReferent>
    <annotation annotator="gold" seType="REPORT" mainReferentGenericity="NON-GENERIC" habituality="EPISODIC" mainVerbAspectualClass="DYNAMIC"/>
    <annotation annotator="B" seType="REPORT:EVENT" mainReferentGenericity="NON-GENERIC" habituality="EPISODIC" mainVerbAspectualClass="DYNAMIC"/>
    <annotation annotator="D" seType="REPORT:EVENT" mainReferentGenericity="NON-GENERIC" habituality="EPISODIC" mainVerbAspectualClass="DYNAMIC"/>
    <annotation annotator="C" seType="REPORT:EVENT" mainReferentGenericity="NON-GENERIC" habituality="EPISODIC" mainVerbAspectualClass="DYNAMIC"/>
  </segment>
  <segment instanceid="news_wsj_0158.txt_11" begin="637" end="678">
    <text>his departure was for "personal reasons,"</text>
    <mainVerb begin="651" end="654">was</mainVerb>
    <mainReferent begin="641" end="650">departure</mainReferent>
    <annotation annotator="gold" seType="STATE" mainReferentGenericity="NON-GENERIC" habituality="STATIC" mainVerbAspectualClass="STATIVE"/>
    <annotation annotator="B" seType="STATE" mainReferentGenericity="NON-GENERIC" habituality="STATIC" mainVerbAspectualClass="STATIVE"/>
    <annotation annotator="D" seType="STATE" mainReferentGenericity="NON-GENERIC" habituality="STATIC" mainVerbAspectualClass="STATIVE"/>
    <annotation annotator="C" seType="STATE" mainReferentGenericity="NON-GENERIC" habituality="STATIC" mainVerbAspectualClass="STATIVE"/>
  </segment>
  <segment instanceid="news_wsj_0158.txt_12" begin="679" end="708">
    <text>which he declined to specify.</text>
    <mainVerb begin="688" end="696">declined</mainVerb>
    <mainReferent begin="685" end="687">he</mainReferent>
    <annotation annotator="gold" seType="EVENT" mainReferentGenericity="NON-GENERIC" habituality="EPISODIC" mainVerbAspectualClass="DYNAMIC"/>
    <annotation annotator="B" seType="EVENT" mainReferentGenericity="NON-GENERIC" habituality="EPISODIC" mainVerbAspectualClass="DYNAMIC"/>
    <annotation annotator="D" seType="EVENT" mainReferentGenericity="NON-GENERIC" habituality="EPISODIC" mainVerbAspectualClass="DYNAMIC"/>
    <annotation annotator="C" seType="EVENT" mainReferentGenericity="NON-GENERIC" habituality="EPISODIC" mainVerbAspectualClass="DYNAMIC"/>
  </segment>
  <segment instanceid="news_wsj_0158.txt_13" begin="709" end="790">
    <text>"There is no business reason for my departure," nor any disagreement over policy,</text>
    <mainVerb begin="716" end="718">is</mainVerb>
    <mainReferent begin="731" end="737">reason</mainReferent>
    <annotation annotator="gold" seType="STATE" mainReferentGenericity="NON-GENERIC" habituality="STATIC" mainVerbAspectualClass="STATIVE"/>
    <annotation annotator="B" seType="STATE" mainReferentGenericity="NON-GENERIC" habituality="STATIC" mainVerbAspectualClass="STATIVE"/>
    <annotation annotator="D" seType="STATE" mainReferentGenericity="NON-GENERIC" habituality="STATIC" mainVerbAspectualClass="STATIVE"/>
    <annotation annotator="C" seType="STATE" mainReferentGenericity="NON-GENERIC" habituality="STATIC" mainVerbAspectualClass="STATIVE"/>
  </segment>
  <segment instanceid="news_wsj_0158.txt_14" begin="791" end="800">
    <text>he added.</text>
    <mainVerb begin="794" end="799">added</mainVerb>
    <mainReferent begin="791" end="793">he</mainReferent>
    <annotation annotator="gold" seType="REPORT" mainReferentGenericity="NON-GENERIC" habituality="EPISODIC" mainVerbAspectualClass="DYNAMIC"/>
    <annotation annotator="B" seType="REPORT:EVENT" mainReferentGenericity="NON-GENERIC" habituality="EPISODIC" mainVerbAspectualClass="DYNAMIC"/>
    <annotation annotator="D" seType="REPORT:EVENT" mainReferentGenericity="NON-GENERIC" habituality="EPISODIC" mainVerbAspectualClass="DYNAMIC"/>
    <annotation annotator="C" seType="REPORT:EVENT" mainReferentGenericity="NON-GENERIC" habituality="EPISODIC" mainVerbAspectualClass="DYNAMIC"/>
  </segment>
  <segment instanceid="news_wsj_0158.txt_15" begin="801" end="825">
    <text>He also rejected reports</text>
    <mainVerb begin="809" end="817">rejected</mainVerb>
    <mainReferent begin="801" end="803">He</mainReferent>
    <annotation annotator="gold" seType="EVENT" mainReferentGenericity="NON-GENERIC" habituality="EPISODIC" mainVerbAspectualClass="DYNAMIC"/>
    <annotation annotator="B" seType="EVENT" mainReferentGenericity="NON-GENERIC" habituality="EPISODIC" mainVerbAspectualClass="DYNAMIC"/>
    <annotation annotator="D" seType="EVENT" mainReferentGenericity="NON-GENERIC" habituality="EPISODIC" mainVerbAspectualClass="DYNAMIC"/>
    <annotation annotator="C" seType="EVENT" mainReferentGenericity="NON-GENERIC" habituality="EPISODIC" mainVerbAspectualClass="DYNAMIC"/>
  </segment>
  <segment instanceid="news_wsj_0158.txt_16" begin="826" end="872">
    <text>that his departure stemmed from disappointment</text>
    <mainVerb begin="845" end="852">stemmed</mainVerb>
    <mainReferent begin="818" end="825">reports</mainReferent>
    <annotation annotator="gold" seType="STATE" mainReferentGenericity="NON-GENERIC" habituality="STATIC" mainVerbAspectualClass="STATIVE"/>
    <annotation annotator="B" seType="STATE" mainReferentGenericity="NON-GENERIC" habituality="STATIC" mainVerbAspectualClass="STATIVE"/>
    <annotation annotator="D" seType="STATE" mainReferentGenericity="NON-GENERIC" habituality="STATIC" mainVerbAspectualClass="STATIVE"/>
    <annotation annotator="C" seType="EVENT" mainReferentGenericity="NON-GENERIC" habituality="EPISODIC" mainVerbAspectualClass="DYNAMIC"/>
  </segment>
  <segment instanceid="news_wsj_0158.txt_17" begin="873" end="978">
    <text>the general manager's post hadn't also led to a board directorship at the London-based news organization.</text>
    <mainVerb begin="912" end="915">led</mainVerb>
    <mainReferent begin="895" end="899">post</mainReferent>
    <annotation annotator="gold" seType="STATE" mainReferentGenericity="NON-GENERIC" habituality="STATIC" mainVerbAspectualClass="DYNAMIC"/>
    <annotation annotator="B" seType="STATE" mainReferentGenericity="NON-GENERIC" habituality="STATIC" mainVerbAspectualClass="DYNAMIC"/>
    <annotation annotator="D" seType="STATE" mainReferentGenericity="NON-GENERIC" habituality="STATIC" mainVerbAspectualClass="STATIVE"/>
    <annotation annotator="C" seType="STATE" mainReferentGenericity="NON-GENERIC" habituality="STATIC" mainVerbAspectualClass="DYNAMIC"/>
  </segment>
  <segment instanceid="news_wsj_0158.txt_18" begin="982" end="1066">
    <text>Mr. Reupke was one of three executives on Reuters's eight-person executive committee</text>
    <mainVerb begin="993" end="996">was</mainVerb>
    <mainReferent begin="986" end="992">Reupke</mainReferent>
    <annotation annotator="gold" seType="STATE" mainReferentGenericity="NON-GENERIC" habituality="STATIC" mainVerbAspectualClass="STATIVE"/>
    <annotation annotator="B" seType="STATE" mainReferentGenericity="NON-GENERIC" habituality="STATIC" mainVerbAspectualClass="STATIVE"/>
    <annotation annotator="D" seType="STATE" mainReferentGenericity="NON-GENERIC" habituality="STATIC" mainVerbAspectualClass="STATIVE"/>
    <annotation annotator="C" seType="STATE" mainReferentGenericity="NON-GENERIC" habituality="STATIC" mainVerbAspectualClass="STATIVE"/>
  </segment>
  <segment instanceid="news_wsj_0158.txt_19" begin="1067" end="1125">
    <text>who didn't also serve on the company's board of directors.</text>
    <mainVerb begin="1083" end="1088">serve</mainVerb>
    <mainReferent begin="1010" end="1020">executives</mainReferent>
    <annotation annotator="gold" seType="STATE" mainReferentGenericity="NON-GENERIC" habituality="STATIC" mainVerbAspectualClass="DYNAMIC"/>
    <annotation annotator="B" seType="STATE" mainReferentGenericity="NON-GENERIC" habituality="STATIC" mainVerbAspectualClass="DYNAMIC"/>
    <annotation annotator="D" seType="STATE" mainReferentGenericity="NON-GENERIC" habituality="STATIC" mainVerbAspectualClass="STATIVE"/>
    <annotation annotator="C" seType="STATE" mainReferentGenericity="NON-GENERIC" habituality="STATIC" mainVerbAspectualClass="DYNAMIC"/>
  </segment>
  <segment instanceid="news_wsj_0158.txt_20" begin="1126" end="1169">
    <text>"If I were choosing the people of tomorrow,</text>
    <mainVerb begin="1137" end="1145">choosing</mainVerb>
    <mainReferent begin="1130" end="1131">I</mainReferent>
    <annotation annotator="gold" seType="STATE" mainReferentGenericity="NON-GENERIC" habituality="STATIC" mainVerbAspectualClass="STATIVE"/>
    <annotation annotator="B" seType="STATE" mainReferentGenericity="NON-GENERIC" habituality="STATIC" mainVerbAspectualClass="STATIVE"/>
    <annotation annotator="D" seType="STATE" mainReferentGenericity="NON-GENERIC" habituality="STATIC" mainVerbAspectualClass="DYNAMIC"/>
    <annotation annotator="C" seType="STATE" mainReferentGenericity="NON-GENERIC" habituality="STATIC" mainVerbAspectualClass="STATIVE"/>
  </segment>
  <segment instanceid="news_wsj_0158.txt_21" begin="1170" end="1200">
    <text>I would have chosen the people</text>
    <mainVerb begin="1183" end="1189">chosen</mainVerb>
    <mainReferent begin="1170" end="1171">I</mainReferent>
    <annotation annotator="gold" seType="STATE" mainReferentGenericity="NON-GENERIC" habituality="STATIC" mainVerbAspectualClass="DYNAMIC"/>
    <annotation annotator="B" seType="STATE" mainReferentGenericity="NON-GENERIC" habituality="STATIC" mainVerbAspectualClass="DYNAMIC"/>
    <annotation annotator="D" seType="STATE" mainReferentGenericity="NON-GENERIC" habituality="STATIC" mainVerbAspectualClass="DYNAMIC"/>
    <annotation annotator="C" seType="STATE" mainReferentGenericity="NON-GENERIC" habituality="STATIC" mainVerbAspectualClass="DYNAMIC"/>
  </segment>
  <segment instanceid="news_wsj_0158.txt_22" begin="1201" end="1227">
    <text>who are now on the board,"</text>
    <mainVerb begin="1205" end="1208">are</mainVerb>
    <mainReferent begin="1194" end="1200">people</mainReferent>
    <annotation annotator="gold" seType="STATE" mainReferentGenericity="NON-GENERIC" habituality="STATIC" mainVerbAspectualClass="STATIVE"/>
    <annotation annotator="B" seType="STATE" mainReferentGenericity="NON-GENERIC" habituality="STATIC" mainVerbAspectualClass="STATIVE"/>
    <annotation annotator="D" seType="STATE" mainReferentGenericity="NON-GENERIC" habituality="STATIC" mainVerbAspectualClass="STATIVE"/>
    <annotation annotator="C" seType="STATE" mainReferentGenericity="NON-GENERIC" habituality="STATIC" mainVerbAspectualClass="STATIVE"/>
  </segment>
  <segment instanceid="news_wsj_0158.txt_23" begin="1228" end="1236">
    <text>he said.</text>
    <mainVerb begin="1231" end="1235">said</mainVerb>
    <mainReferent begin="1228" end="1230">he</mainReferent>
    <annotation annotator="gold" seType="REPORT" mainReferentGenericity="NON-GENERIC" habituality="EPISODIC" mainVerbAspectualClass="DYNAMIC"/>
    <annotation annotator="B" seType="REPORT:EVENT" mainReferentGenericity="NON-GENERIC" habituality="EPISODIC" mainVerbAspectualClass="DYNAMIC"/>
    <annotation annotator="D" seType="REPORT:EVENT" mainReferentGenericity="NON-GENERIC" habituality="EPISODIC" mainVerbAspectualClass="DYNAMIC"/>
    <annotation annotator="C" seType="REPORT:EVENT" mainReferentGenericity="NON-GENERIC" habituality="EPISODIC" mainVerbAspectualClass="DYNAMIC"/>
  </segment>
  <segment instanceid="news_wsj_0158.txt_24" begin="1240" end="1264">
    <text>A Reuters spokesman said</text>
    <mainVerb begin="1260" end="1264">said</mainVerb>
    <mainReferent begin="1250" end="1259">spokesman</mainReferent>
    <annotation annotator="gold" seType="REPORT" mainReferentGenericity="NON-GENERIC" habituality="EPISODIC" mainVerbAspectualClass="DYNAMIC"/>
    <annotation annotator="B" seType="REPORT:EVENT" mainReferentGenericity="NON-GENERIC" habituality="EPISODIC" mainVerbAspectualClass="DYNAMIC"/>
    <annotation annotator="D" seType="REPORT:EVENT" mainReferentGenericity="NON-GENERIC" habituality="EPISODIC" mainVerbAspectualClass="DYNAMIC"/>
    <annotation annotator="C" seType="REPORT:EVENT" mainReferentGenericity="NON-GENERIC" habituality="EPISODIC" mainVerbAspectualClass="DYNAMIC"/>
  </segment>
  <segment instanceid="news_wsj_0158.txt_25" begin="1265" end="1323">
    <text>the departure reflects "no change in strategy or profits."</text>
    <mainVerb begin="1279" end="1287">reflects</mainVerb>
    <mainReferent begin="1269" end="1278">departure</mainReferent>
    <annotation annotator="gold" seType="STATE" mainReferentGenericity="NON-GENERIC" habituality="STATIC" mainVerbAspectualClass="STATIVE"/>
    <annotation annotator="B" seType="STATE" mainReferentGenericity="NON-GENERIC" habituality="STATIC" mainVerbAspectualClass="STATIVE"/>
    <annotation annotator="D" seType="STATE" mainReferentGenericity="NON-GENERIC" habituality="STATIC" mainVerbAspectualClass="STATIVE"/>
    <annotation annotator="C" seType="EVENT" mainReferentGenericity="NON-GENERIC" habituality="EPISODIC" mainVerbAspectualClass="DYNAMIC"/>
  </segment>
  <segment instanceid="news_wsj_0158.txt_26" begin="1324" end="1389">
    <text>Mark Shepperd, an analyst at UBS Phillips &amp; Drew in London, said,</text>
    <mainVerb begin="1384" end="1388">said</mainVerb>
    <mainReferent begin="1329" end="1337">Shepperd</mainReferent>
    <annotation annotator="gold" seType="REPORT" mainReferentGenericity="NON-GENERIC" habituality="EPISODIC" mainVerbAspectualClass="DYNAMIC"/>
    <annotation annotator="B" seType="REPORT:EVENT" mainReferentGenericity="NON-GENERIC" habituality="EPISODIC" mainVerbAspectualClass="DYNAMIC"/>
    <annotation annotator="D" seType="REPORT:EVENT" mainReferentGenericity="NON-GENERIC" habituality="EPISODIC" mainVerbAspectualClass="DYNAMIC"/>
    <annotation annotator="C" seType="REPORT:EVENT" mainReferentGenericity="NON-GENERIC" habituality="EPISODIC" mainVerbAspectualClass="DYNAMIC"/>
  </segment>
  <segment instanceid="news_wsj_0158.txt_27" begin="1390" end="1400">
    <text>"I suspect</text>
    <mainVerb begin="1393" end="1400">suspect</mainVerb>
    <mainReferent begin="1391" end="1392">I</mainReferent>
    <annotation annotator="gold" seType="STATE" mainReferentGenericity="NON-GENERIC" habituality="STATIC" mainVerbAspectualClass="STATIVE"/>
    <annotation annotator="B" seType="STATE" mainReferentGenericity="NON-GENERIC" habituality="STATIC" mainVerbAspectualClass="STATIVE"/>
    <annotation annotator="D" seType="STATE" mainReferentGenericity="NON-GENERIC" habituality="STATIC" mainVerbAspectualClass="STATIVE"/>
    <annotation annotator="C" seType="STATE" mainReferentGenericity="NON-GENERIC" habituality="STATIC" mainVerbAspectualClass="STATIVE"/>
  </segment>
  <segment instanceid="news_wsj_0158.txt_28" begin="1401" end="1459">
    <text>(the departure) will be fairly irrelevant for the company.</text>
    <mainVerb begin="1422" end="1424">be</mainVerb>
    <mainReferent begin="1406" end="1415">departure</mainReferent>
    <annotation annotator="gold" seType="STATE" mainReferentGenericity="NON-GENERIC" habituality="STATIC" mainVerbAspectualClass="STATIVE"/>
    <annotation annotator="B" seType="PROPOSITION:ABSTRACT_ENTITY:STATE" mainReferentGenericity="NON-GENERIC" habituality="STATIC" mainVerbAspectualClass="STATIVE"/>
    <annotation annotator="D" seType="PROPOSITION:ABSTRACT_ENTITY:STATE" mainReferentGenericity="NON-GENERIC" habituality="STATIC" mainVerbAspectualClass="STATIVE"/>
    <annotation annotator="C" seType="PROPOSITION:ABSTRACT_ENTITY:STATE" mainReferentGenericity="NON-GENERIC" habituality="STATIC" mainVerbAspectualClass="STATIVE"/>
  </segment>
  <segment instanceid="news_wsj_0158.txt_29" begin="1460" end="1485">
    <text>I would be very surprised</text>
    <mainVerb begin="1476" end="1485">surprised</mainVerb>
    <mainReferent begin="1460" end="1461">I</mainReferent>
    <annotation annotator="gold" seType="STATE" mainReferentGenericity="NON-GENERIC" habituality="STATIC" mainVerbAspectualClass="STATIVE"/>
    <annotation annotator="B" seType="STATE" mainReferentGenericity="NON-GENERIC" habituality="STATIC" mainVerbAspectualClass="STATIVE"/>
    <annotation annotator="D" seType="STATE" mainReferentGenericity="NON-GENERIC" habituality="STATIC" mainVerbAspectualClass="STATIVE"/>
    <annotation annotator="C" seType="STATE" mainReferentGenericity="NON-GENERIC" habituality="STATIC" mainVerbAspectualClass="STATIVE"/>
  </segment>
  <segment instanceid="news_wsj_0158.txt_30" begin="1486" end="1568">
    <text>if his departure signals any change in strategy or change in profit expectations."</text>
    <mainVerb begin="1503" end="1510">signals</mainVerb>
    <mainReferent begin="1493" end="1502">departure</mainReferent>
    <annotation annotator="gold" seType="STATE" mainReferentGenericity="NON-GENERIC" habituality="STATIC" mainVerbAspectualClass="DYNAMIC"/>
    <annotation annotator="B" seType="STATE" mainReferentGenericity="NON-GENERIC" habituality="STATIC" mainVerbAspectualClass="DYNAMIC"/>
    <annotation annotator="D" seType="STATE" mainReferentGenericity="NON-GENERIC" habituality="STATIC" mainVerbAspectualClass="STATIVE"/>
    <annotation annotator="C" seType="STATE" mainReferentGenericity="NON-GENERIC" habituality="STATIC" mainVerbAspectualClass="DYNAMIC"/>
  </segment>
  <segment instanceid="news_wsj_0158.txt_31" begin="1569" end="1650">
    <text>On London's Stock Exchange, Reuters shares rose five pence to 913 pence ($14.43).</text>
    <mainVerb begin="1612" end="1616">rose</mainVerb>
    <mainReferent begin="1605" end="1611">shares</mainReferent>
    <annotation annotator="gold" seType="EVENT" mainReferentGenericity="NON-GENERIC" habituality="EPISODIC" mainVerbAspectualClass="DYNAMIC"/>
    <annotation annotator="B" seType="EVENT" mainReferentGenericity="NON-GENERIC" habituality="EPISODIC" mainVerbAspectualClass="DYNAMIC"/>
    <annotation annotator="D" seType="EVENT" mainReferentGenericity="NON-GENERIC" habituality="EPISODIC" mainVerbAspectualClass="DYNAMIC"/>
    <annotation annotator="C" seType="EVENT" mainReferentGenericity="NON-GENERIC" habituality="EPISODIC" mainVerbAspectualClass="DYNAMIC"/>
  </segment>
  <segment instanceid="news_wsj_0158.txt_32" begin="1651" end="1809">
    <text>In the U.S. over-the-counter market, American depositary shares for Reuters, each representing three shares in the London market, closed unchanged at $43.875.</text>
    <mainVerb begin="1781" end="1787">closed</mainVerb>
    <mainReferent begin="1708" end="1714">shares</mainReferent>
    <annotation annotator="gold" seType="EVENT" mainReferentGenericity="NON-GENERIC" habituality="EPISODIC" mainVerbAspectualClass="DYNAMIC"/>
    <annotation annotator="B" seType="EVENT" mainReferentGenericity="NON-GENERIC" habituality="EPISODIC" mainVerbAspectualClass="DYNAMIC"/>
    <annotation annotator="D" seType="EVENT" mainReferentGenericity="NON-GENERIC" habituality="EPISODIC" mainVerbAspectualClass="DYNAMIC"/>
    <annotation annotator="C" seType="EVENT" mainReferentGenericity="NON-GENERIC" habituality="EPISODIC" mainVerbAspectualClass="DYNAMIC"/>
  </segment>
  <segment instanceid="news_wsj_0158.txt_33" begin="1813" end="1950">
    <text>The senior of the three executives who will assume Mr. Reupke's duties is Nigel Judah, 58, finance director and a Reuters board director.</text>
    <mainVerb begin="1884" end="1886">is</mainVerb>
    <mainReferent begin="1817" end="1823">senior</mainReferent>
    <annotation annotator="gold" seType="STATE" mainReferentGenericity="NON-GENERIC" habituality="STATIC" mainVerbAspectualClass="STATIVE"/>
    <annotation annotator="B" seType="STATE" mainReferentGenericity="NON-GENERIC" habituality="STATIC" mainVerbAspectualClass="STATIVE"/>
    <annotation annotator="D" seType="STATE" mainReferentGenericity="NON-GENERIC" habituality="STATIC" mainVerbAspectualClass="STATIVE"/>
    <annotation annotator="C" seType="STATE" mainReferentGenericity="NON-GENERIC" habituality="STATIC" mainVerbAspectualClass="DYNAMIC"/>
  </segment>
  <segment instanceid="news_wsj_0158.txt_34" begin="1951" end="2032">
    <text>Peter Holland, 45, deputy general manager, becomes director of corporate affairs.</text>
    <mainVerb begin="1994" end="2001">becomes</mainVerb>
    <mainReferent begin="1957" end="1964">Holland</mainReferent>
    <annotation annotator="gold" seType="STATE" mainReferentGenericity="NON-GENERIC" habituality="STATIC" mainVerbAspectualClass="DYNAMIC"/>
    <annotation annotator="B" seType="STATE" mainReferentGenericity="NON-GENERIC" habituality="STATIC" mainVerbAspectualClass="DYNAMIC"/>
    <annotation annotator="D" seType="EVENT" mainReferentGenericity="NON-GENERIC" habituality="EPISODIC" mainVerbAspectualClass="DYNAMIC"/>
    <annotation annotator="C" seType="STATE" mainReferentGenericity="NON-GENERIC" habituality="STATIC" mainVerbAspectualClass="DYNAMIC"/>
  </segment>
  <segment instanceid="news_wsj_0158.txt_35" begin="2033" end="2133">
    <text>And Patrick Mannix, 46, international technical manager, becomes director of group quality programs.</text>
    <mainVerb begin="2090" end="2097">becomes</mainVerb>
    <mainReferent begin="2045" end="2051">Mannix</mainReferent>
    <annotation annotator="gold" seType="STATE" mainReferentGenericity="NON-GENERIC" habituality="STATIC" mainVerbAspectualClass="DYNAMIC"/>
    <annotation annotator="B" seType="STATE" mainReferentGenericity="NON-GENERIC" habituality="STATIC" mainVerbAspectualClass="DYNAMIC"/>
    <annotation annotator="D" seType="EVENT" mainReferentGenericity="NON-GENERIC" habituality="EPISODIC" mainVerbAspectualClass="DYNAMIC"/>
    <annotation annotator="C" seType="STATE" mainReferentGenericity="NON-GENERIC" habituality="STATIC" mainVerbAspectualClass="DYNAMIC"/>
  </segment>
</document>
